rustat_python_api/__init__.py
rustat_python_api/config.py
rustat_python_api/models_api.py
rustat_python_api/parser.py
rustat_python_api/pitch_control.py
rustat_python_api/processing.py
rustat_python_api/urls.py
rustat_python_api/kernels/__init__.py
rustat_python_api/kernels/maha.py
rustat_python_api/matching/__init__.py
rustat_python_api/matching/dataloader.py
rustat_python_api/matching/pc_adder.py
rustat_python_api/matching/tr_adder.py
rustat_python_api-0.7.11.dist-info/LICENSE
rustat_python_api-0.7.11.dist-info/METADATA
rustat_python_api-0.7.11.dist-info/WHEEL
rustat_python_api-0.7.11.dist-info/top_level.txt
rustat_python_api-0.7.11.dist-info/RECORD
