Metadata-Version: 2.1
Name: rustat-python-api
Version: 0.7.11
Summary: A Python wrapper for RuStat API
Home-page: https://github.com/dailydaniel/rustat-python-api
Author: Daniel Zholkovsky
Author-email: daniel@zholkovsky.com
License: MIT
Classifier: Programming Language :: Python :: 3
Classifier: License :: OSI Approved :: MIT License
Classifier: Operating System :: OS Independent
Requires-Python: >=3.10
License-File: LICENSE
Requires-Dist: requests==2.32.3
Requires-Dist: pandas==2.2.3
Requires-Dist: tqdm==4.66.5
Requires-Dist: scipy==1.14.1
Requires-Dist: matplotlib
Requires-Dist: matplotsoccer
Provides-Extra: cpu
Requires-Dist: torch; extra == "cpu"
Provides-Extra: gpu
Requires-Dist: torch; extra == "gpu"
Requires-Dist: triton==3.0.0; platform_system == "Linux" and extra == "gpu"
